Tangly/__init__.py
Tangly-5.1.dist-info/METADATA
Tangly-5.1.dist-info/WHEEL
Tangly-5.1.dist-info/top_level.txt
Tangly-5.1.dist-info/RECORD
