Metadata-Version: 2.1
Name: Tangly
Version: 5.1
Author: Rafa Rayes
Author-email: rafa@rayes.com.br
License: MIT
Classifier: Programming Language :: Python :: 3
Classifier: License :: OSI Approved :: MIT License
Classifier: Operating System :: OS Independent
